youtube_websearch/__init__.py
youtube_websearch-1.0.1.dist-info/LICENSE
youtube_websearch-1.0.1.dist-info/METADATA
youtube_websearch-1.0.1.dist-info/WHEEL
youtube_websearch-1.0.1.dist-info/top_level.txt
youtube_websearch-1.0.1.dist-info/RECORD
